hodl/__init__.py
hodl/cli.py
hodl_cb-0.1.0.dist-info/LICENSE
hodl_cb-0.1.0.dist-info/METADATA
hodl_cb-0.1.0.dist-info/WHEEL
hodl_cb-0.1.0.dist-info/entry_points.txt
hodl_cb-0.1.0.dist-info/top_level.txt
hodl_cb-0.1.0.dist-info/RECORD
