Metadata-Version: 2.1
Name: hodl-cb
Version: 0.1.0
Summary: Cryptocurrency dollar-cost averaging on the CLI (via the Coinbase Advanced API).
Home-page: http://github.com/nonfungible_dev/hodl
Author: NFP
Author-email: nfp@pesky-penguins.com
Classifier: Development Status :: 3 - Alpha
Classifier: Intended Audience :: Developers
Classifier: License :: OSI Approved :: MIT License
Classifier: Programming Language :: Python :: 3
Classifier: Programming Language :: Python :: 3.7
Classifier: Programming Language :: Python :: 3.8
Classifier: Programming Language :: Python :: 3.9
License-File: LICENSE
Requires-Dist: click
Requires-Dist: coinbase-advanced-py
